Metadata-Version: 2.4
Name: loki-console-logger-python
Version: 1.0.12
Summary: Ultra-performant Loki logger for Python applications async (FastAPI, asyncio) and sync (scripts, Django, etc.) environments.
Project-URL: Homepage, https://github.com/elvenobservability/loki-console-logger-python
Project-URL: Bug Tracker, https://github.com/elvenobservability/loki-console-logger-python/issues
Author-email: Leonardo Zwirtes <leonardo.zwirtes@elven.works>
License: MIT
Keywords: aiohttp,asyncio,grafana,logging,loki,observability,sync
Classifier: License :: OSI Approved :: MIT License
Classifier: Operating System :: OS Independent
Classifier: Programming Language :: Python :: 3
Requires-Python: >=3.6
Requires-Dist: aiohttp>=2.0.0
Requires-Dist: opentelemetry-api>=1.13.0
